{
  "data": [
    {
      "set": "base5",
      "cardNum": "1",
      "name": "Dark Alakazam",
      "artist": "Ken Sugimori",
      "supertype": "Pokémon",
      "flavorText": "Almost as if it were being controlled by something else, it never changes expressions, even in the middle of battle.",
      "types": [
        "Psychic"
      ],
      "subtypes": [
        "Stage 2"
      ],
      "hp": "60",
      "level": "30",
      "evolvesFrom": "Dark Kadabra",
      "rarity": "Rare Holo",
      "attacks": [
        {
          "name": "Teleport Blast",
          "cost": [
            "Psychic",
            "Psychic",
            "Colorless"
          ],
          "convertedEnergyCost": 3,
          "damage": "30",
          "text": "You may switch Dark Alakazam with 1 of your Benched Pokémon. (Do the damage before switching the Pokémon.)"
        },
        {
          "name": "Mind Shock",
          "cost": [
            "Psychic",
            "Psychic",
            "Psychic"
          ],
          "convertedEnergyCost": 3,
          "damage": "40",
          "text": "Don't apply Weakness and Resistance for this attack. (Any other effects that would happen after applying Weakness and Resistance still happen.)"
        }
      ],
      "weaknesses": [
        {
          "type": "Psychic",
          "value": "×2"
        }
      ],
      "retreatCost": [
        "Colorless",
        "Colorless",
        "Colorless"
      ],
      "pokedexNumbers": [
        65
      ]
    },
    {
      "set": "base5",
      "cardNum": "2",
      "name": "Dark Arbok",
      "artist": "Mitsuhiro Arita",
      "supertype": "Pokémon",
      "flavorText": "Freezes its prey with its stare. If you should encounter one, remember not to look into its eyes.",
      "types": [
        "Grass"
      ],
      "subtypes": [
        "Stage 1"
      ],
      "hp": "60",
      "level": "25",
      "evolvesFrom": "Ekans",
      "rarity": "Rare Holo",
      "attacks": [
        {
          "name": "Stare",
          "cost": [
            "Grass",
            "Grass"
          ],
          "convertedEnergyCost": 2,
          "damage": "",
          "text": "Choose 1 of your opponent's Pokémon. This attack does 10 damage to that Pokémon. Don't apply Weakness and Resistance for this attack. (Any other effects that would happen after applying Weakness and Resistance still happen.) If that Pokémon has a Pokémon Power, that power stops working until the end of your opponent's next turn."
        },
        {
          "name": "Poison Vapor",
          "cost": [
            "Grass",
            "Grass",
            "Grass"
          ],
          "convertedEnergyCost": 3,
          "damage": "10",
          "text": "The Defending Pokémon is now Poisoned. This attack does 10 damage to each of your opponent's Benched Pokémon. (Don't apply Weakness and Resistance for Benched Pokémon.)"
        }
      ],
      "weaknesses": [
        {
          "type": "Psychic",
          "value": "×2"
        }
      ],
      "retreatCost": [
        "Colorless",
        "Colorless"
      ],
      "pokedexNumbers": [
        24
      ]
    },
    {
      "set": "base5",
      "cardNum": "3",
      "name": "Dark Blastoise",
      "artist": "Mitsuhiro Arita",
      "supertype": "Pokémon",
      "flavorText": "An aggressive Pokémon that tackles anything it sees.",
      "types": [
        "Water"
      ],
      "subtypes": [
        "Stage 2"
      ],
      "hp": "70",
      "level": "28",
      "evolvesFrom": "Dark Wartortle",
      "rarity": "Rare Holo",
      "attacks": [
        {
          "name": "Hydrocannon",
          "cost": [
            "Water",
            "Water"
          ],
          "convertedEnergyCost": 2,
          "damage": "30+",
          "text": "Does 30 damage plus 20 more damage for each Water Energy attached to Dark Blastoise but not used to pay for this attack. You can't add more than 40 damage in this way."
        },
        {
          "name": "Rocket Tackle",
          "cost": [
            "Water",
            "Colorless",
            "Colorless"
          ],
          "convertedEnergyCost": 3,
          "damage": "40",
          "text": "Dark Blastoise does 10 damage to itself. Flip a coin. If heads, prevent all damage done to Dark Blastoise during your opponent's next turn. (Any other effects of attacks still happen.)"
        }
      ],
      "weaknesses": [
        {
          "type": "Lightning",
          "value": "×2"
        }
      ],
      "retreatCost": [
        "Colorless",
        "Colorless"
      ],
      "pokedexNumbers": [
        9
      ]
    },
    {
      "set": "base5",
      "cardNum": "4",
      "name": "Dark Charizard",
      "artist": "Ken Sugimori",
      "supertype": "Pokémon",
      "flavorText": "Seemingly possessed, it spews fire like a volcano, trying to burn all it sees.",
      "types": [
        "Fire"
      ],
      "subtypes": [
        "Stage 2"
      ],
      "hp": "80",
      "level": "38",
      "evolvesFrom": "Dark Charmeleon",
      "rarity": "Rare Holo",
      "attacks": [
        {
          "name": "Nail Flick",
          "cost": [
            "Colorless"
          ],
          "convertedEnergyCost": 1,
          "damage": "10",
          "text": ""
        },
        {
          "name": "Continuous Fireball",
          "cost": [
            "Fire",
            "Fire"
          ],
          "convertedEnergyCost": 2,
          "damage": "50×",
          "text": "Flip a number of coins equal to the number of Fire Energy cards attached to Dark Charizard. This attack does 50 damage times the number of heads. Discard a number of Fire Energy cards attached to Dark Charizard equal to the number of heads."
        }
      ],
      "weaknesses": [
        {
          "type": "Water",
          "value": "×2"
        }
      ],
      "resistances": [
        {
          "type": "Fighting",
          "value": "-30"
        }
      ],
      "retreatCost": [
        "Colorless",
        "Colorless",
        "Colorless"
      ],
      "pokedexNumbers": [
        6
      ]
    },
    {
      "set": "base5",
      "cardNum": "5",
      "name": "Dark Dragonite",
      "artist": "Mitsuhiro Arita",
      "supertype": "Pokémon",
      "flavorText": "Sometimes called \"The God of Destruction.\" Its wings are able to support it in spite of its massive weight.",
      "types": [
        "Colorless"
      ],
      "subtypes": [
        "Stage 2"
      ],
      "hp": "70",
      "level": "33",
      "evolvesFrom": "Dark Dragonair",
      "rarity": "Rare Holo",
      "abilities": [
        {
          "name": "Summon Minions",
          "text": "When you play Dark Dragonite from your hand, search your deck for up to 2 Basic Pokémon and put them onto your Bench. Shuffle your deck afterward.",
          "type": "Pokémon Power"
        }
      ],
      "attacks": [
        {
          "name": "Giant Tail",
          "cost": [
            "Colorless",
            "Colorless",
            "Colorless",
            "Colorless"
          ],
          "convertedEnergyCost": 4,
          "damage": "70",
          "text": "Flip a coin. If tails, this attack does nothing."
        }
      ],
      "resistances": [
        {
          "type": "Fighting",
          "value": "-30"
        }
      ],
      "retreatCost": [
        "Colorless",
        "Colorless"
      ],
      "pokedexNumbers": [
        149
      ]
    },
    {
      "set": "base5",
      "cardNum": "7",
      "name": "Dark Golbat",
      "artist": "Mitsuhiro Arita",
      "supertype": "Pokémon",
      "flavorText": "Sneaks up silently on its prey and attacks it from behind, sometimes killing it with one bite.",
      "types": [
        "Grass"
      ],
      "subtypes": [
        "Stage 1"
      ],
      "hp": "50",
      "level": "25",
      "evolvesFrom": "Zubat",
      "evolvesTo": [
        "Crobat"
      ],
      "rarity": "Rare Holo",
      "abilities": [
        {
          "name": "Sneak Attack",
          "text": "When you play Dark Golbat from your hand, you may choose 1 of your opponent's Pokémon. If you do, Dark Golbat does 10 damage to that Pokémon. Apply Weakness and Resistance.",
          "type": "Pokémon Power"
        }
      ],
      "attacks": [
        {
          "name": "Flitter",
          "cost": [
            "Grass",
            "Grass"
          ],
          "convertedEnergyCost": 2,
          "damage": "",
          "text": "Choose 1 of your opponent's Pokémon. This attack does 20 damage to that Pokémon. Don't apply Weakness and Resistance for this attack. (Any other effects that would happen after applying Weakness and Resistance still happen.)"
        }
      ],
      "weaknesses": [
        {
          "type": "Psychic",
          "value": "×2"
        }
      ],
      "resistances": [
        {
          "type": "Fighting",
          "value": "-30"
        }
      ],
      "pokedexNumbers": [
        42
      ]
    },
    {
      "set": "base5",
      "cardNum": "6",
      "name": "Dark Dugtrio",
      "artist": "Kagemaru Himeno",
      "supertype": "Pokémon",
      "flavorText": "Digs large sinkholes in the ground and tries to trap its enemies in them.",
      "types": [
        "Fighting"
      ],
      "subtypes": [
        "Stage 1"
      ],
      "hp": "50",
      "level": "18",
      "evolvesFrom": "Diglett",
      "rarity": "Rare Holo",
      "abilities": [
        {
          "name": "Sinkhole",
          "text": "Whenever your opponent's Active Pokémon retreats, your opponent flips a coin. If tails, this power does 20 damage to that Pokémon. (Don't apply Weakness and Resistance.) This power stops working while Dark Dugtrio is Asleep, Confused, or Paralyzed.",
          "type": "Pokémon Power"
        }
      ],
      "attacks": [
        {
          "name": "Knock Down",
          "cost": [
            "Fighting",
            "Fighting"
          ],
          "convertedEnergyCost": 2,
          "damage": "20+",
          "text": "Your opponent flips a coin. If tails, this attack does 20 damage plus 20 more damage; if heads, this attack does 20 damage."
        }
      ],
      "weaknesses": [
        {
          "type": "Grass",
          "value": "×2"
        }
      ],
      "resistances": [
        {
          "type": "Lightning",
          "value": "-30"
        }
      ],
      "retreatCost": [
        "Colorless",
        "Colorless"
      ],
      "pokedexNumbers": [
        51
      ]
    },
    {
      "set": "base5",
      "cardNum": "8",
      "name": "Dark Gyarados",
      "artist": "Kagemaru Himeno",
      "supertype": "Pokémon",
      "flavorText": "Normally found only in the deep ocean, it has recently been seen in shallow waters as well.",
      "types": [
        "Water"
      ],
      "subtypes": [
        "Stage 1"
      ],
      "hp": "70",
      "level": "31",
      "evolvesFrom": "Magikarp",
      "rarity": "Rare Holo",
      "abilities": [
        {
          "name": "Final Beam",
          "text": "When Dark Gyarados is Knocked Out by an attack, flip a coin. If heads, this power does 20 damage for each Water Energy attached to Dark Gyarados to the Pokémon that Knocked Out Dark Gyarados. Apply Weakness and Resistance. This power doesn't work if Dark Gyarados is Asleep, Confused, or Paralyzed.",
          "type": "Pokémon Power"
        }
      ],
      "attacks": [
        {
          "name": "Ice Beam",
          "cost": [
            "Water",
            "Water",
            "Water"
          ],
          "convertedEnergyCost": 3,
          "damage": "30",
          "text": "Flip a coin. If heads, the Defending Pokémon is now Paralyzed."
        }
      ],
      "weaknesses": [
        {
          "type": "Grass",
          "value": "×2"
        }
      ],
      "resistances": [
        {
          "type": "Fighting",
          "value": "-30"
        }
      ],
      "retreatCost": [
        "Colorless",
        "Colorless"
      ],
      "pokedexNumbers": [
        130
      ]
    },
    {
      "set": "base5",
      "cardNum": "9",
      "name": "Dark Hypno",
      "artist": "Kagemaru Himeno",
      "supertype": "Pokémon",
      "flavorText": "Carries a pendulum with it always. Sometimes appears near less-traveled roads and schools at dusk.",
      "types": [
        "Psychic"
      ],
      "subtypes": [
        "Stage 1"
      ],
      "hp": "60",
      "level": "26",
      "evolvesFrom": "Drowzee",
      "rarity": "Rare Holo",
      "attacks": [
        {
          "name": "Psypunch",
          "cost": [
            "Psychic"
          ],
          "convertedEnergyCost": 1,
          "damage": "20",
          "text": ""
        },
        {
          "name": "Bench Manipulation",
          "cost": [
            "Psychic",
            "Psychic",
            "Colorless"
          ],
          "convertedEnergyCost": 3,
          "damage": "20×",
          "text": "Your opponent flips a number of coins equal to the number of Pokémon on his or her Bench. This attack does 20 damage times the number of tails. Don't apply Weakness and Resistance for this attack. (Any other effects that would happen after applying Weakness and Resistance still happen.)"
        }
      ],
      "weaknesses": [
        {
          "type": "Psychic",
          "value": "×2"
        }
      ],
      "retreatCost": [
        "Colorless",
        "Colorless"
      ],
      "pokedexNumbers": [
        97
      ]
    },
    {
      "set": "base5",
      "cardNum": "11",
      "name": "Dark Magneton",
      "artist": "Miki Tanaka",
      "supertype": "Pokémon",
      "flavorText": "The number of incidents of hackers using Magnetons to damage computer systems is steadily increasing.",
      "types": [
        "Lightning"
      ],
      "subtypes": [
        "Stage 1"
      ],
      "hp": "60",
      "level": "26",
      "evolvesFrom": "Magnemite",
      "evolvesTo": [
        "Magnezone"
      ],
      "rarity": "Rare Holo",
      "attacks": [
        {
          "name": "Sonicboom",
          "cost": [
            "Colorless",
            "Colorless"
          ],
          "convertedEnergyCost": 2,
          "damage": "20",
          "text": "Don't apply Weakness and Resistance for this attack. (Any other effects that would happen after applying Weakness and Resistance still happen.)"
        },
        {
          "name": "Magnetic Lines",
          "cost": [
            "Lightning",
            "Lightning"
          ],
          "convertedEnergyCost": 2,
          "damage": "30",
          "text": "If the Defending Pokémon has any basic Energy cards attached to it, choose 1 of them. If your opponent has any Benched Pokémon, choose 1 of them and attach that Energy card to it."
        }
      ],
      "weaknesses": [
        {
          "type": "Fighting",
          "value": "×2"
        }
      ],
      "retreatCost": [
        "Colorless",
        "Colorless"
      ],
      "pokedexNumbers": [
        82
      ]
    },
    {
      "set": "base5",
      "cardNum": "10",
      "name": "Dark Machamp",
      "artist": "Mitsuhiro Arita",
      "supertype": "Pokémon",
      "flavorText": "It is almost impossible to defend against a Machamp's four powerful arms.",
      "types": [
        "Fighting"
      ],
      "subtypes": [
        "Stage 2"
      ],
      "hp": "70",
      "level": "30",
      "evolvesFrom": "Dark Machoke",
      "rarity": "Rare Holo",
      "attacks": [
        {
          "name": "Mega Punch",
          "cost": [
            "Fighting",
            "Fighting"
          ],
          "convertedEnergyCost": 2,
          "damage": "30",
          "text": ""
        },
        {
          "name": "Fling",
          "cost": [
            "Fighting",
            "Fighting",
            "Fighting",
            "Colorless"
          ],
          "convertedEnergyCost": 4,
          "damage": "",
          "text": "Your opponent shuffles his or her Active Pokémon and all cards attached to it into his or her deck. This attack can't be used if your opponent has no Benched Pokémon."
        }
      ],
      "weaknesses": [
        {
          "type": "Psychic",
          "value": "×2"
        }
      ],
      "retreatCost": [
        "Colorless",
        "Colorless",
        "Colorless"
      ],
      "pokedexNumbers": [
        68
      ]
    },
    {
      "set": "base5",
      "cardNum": "12",
      "name": "Dark Slowbro",
      "artist": "Mitsuhiro Arita",
      "supertype": "Pokémon",
      "flavorText": "It loves nothing better than to be left alone, and so sometimes ends up being manipulated by unscrupulous people.",
      "types": [
        "Psychic"
      ],
      "subtypes": [
        "Stage 1"
      ],
      "hp": "60",
      "level": "27",
      "evolvesFrom": "Slowpoke",
      "rarity": "Rare Holo",
      "abilities": [
        {
          "name": "Reel In",
          "text": "When you play Dark Slowbro from your hand, choose up to 3 Basic Pokémon and/or Evolution cards from your discard pile and put them into your hand.",
          "type": "Pokémon Power"
        }
      ],
      "attacks": [
        {
          "name": "Fickle Attack",
          "cost": [
            "Psychic",
            "Psychic"
          ],
          "convertedEnergyCost": 2,
          "damage": "40",
          "text": "Flip a coin. If tails, this attack does nothing."
        }
      ],
      "weaknesses": [
        {
          "type": "Psychic",
          "value": "×2"
        }
      ],
      "retreatCost": [
        "Colorless",
        "Colorless"
      ],
      "pokedexNumbers": [
        80
      ]
    },
    {
      "set": "base5",
      "cardNum": "14",
      "name": "Dark Weezing",
      "artist": "Shin-ichi Yoshida",
      "supertype": "Pokémon",
      "flavorText": "Researchers have observed these Pokémon reproducing in industrial waste sites.",
      "types": [
        "Grass"
      ],
      "subtypes": [
        "Stage 1"
      ],
      "hp": "60",
      "level": "24",
      "evolvesFrom": "Koffing",
      "rarity": "Rare Holo",
      "attacks": [
        {
          "name": "Mass Explosion",
          "cost": [
            "Grass",
            "Colorless"
          ],
          "convertedEnergyCost": 2,
          "damage": "20×",
          "text": "Does 20 damage times the total number of Koffings, Weezings, and Dark Weezings in play (Apply Weakness and Resistance.). Then, this attack does 20 damage to each Koffing, Weezing, and Dark Weezing (even your own). Don't apply Weakness and Resistance."
        },
        {
          "name": "Stun Gas",
          "cost": [
            "Grass",
            "Grass",
            "Grass"
          ],
          "convertedEnergyCost": 3,
          "damage": "20",
          "text": "Flip a coin. If heads, the Defending Pokémon is now Poisoned; if tails, the Defending Pokémon is now Paralyzed."
        }
      ],
      "weaknesses": [
        {
          "type": "Psychic",
          "value": "×2"
        }
      ],
      "retreatCost": [
        "Colorless"
      ],
      "pokedexNumbers": [
        110
      ]
    },
    {
      "set": "base5",
      "cardNum": "13",
      "name": "Dark Vileplume",
      "artist": "Kagemaru Himeno",
      "supertype": "Pokémon",
      "flavorText": "Perhaps because of their strong-smelling pollen, other Pokémon do not approach areas where Vileplumes live.",
      "types": [
        "Grass"
      ],
      "subtypes": [
        "Stage 2"
      ],
      "hp": "60",
      "level": "29",
      "evolvesFrom": "Dark Gloom",
      "rarity": "Rare Holo",
      "abilities": [
        {
          "name": "Hay Fever",
          "text": "No Trainer cards can be played. This power stops working while Dark Vileplume is Asleep, Confused, or Paralyzed.",
          "type": "Pokémon Power"
        }
      ],
      "attacks": [
        {
          "name": "Petal Whirlwind",
          "cost": [
            "Grass",
            "Grass",
            "Grass"
          ],
          "convertedEnergyCost": 3,
          "damage": "30×",
          "text": "Flip a coins. This attack does 30 damage times the number of heads. If you get 2 or more heads, Dark Vileplume is now Confused (after doing damage)."
        }
      ],
      "weaknesses": [
        {
          "type": "Fire",
          "value": "×2"
        }
      ],
      "retreatCost": [
        "Colorless",
        "Colorless"
      ],
      "pokedexNumbers": [
        45
      ]
    },
    {
      "set": "base5",
      "cardNum": "15",
      "name": "Here Comes Team Rocket!",
      "artist": "Ken Sugimori",
      "supertype": "Trainer",
      "rules": [
        "Each player plays with his or her Prize cards face up for the rest of the game."
      ],
      "rarity": "Rare Holo"
    },
    {
      "set": "base5",
      "cardNum": "17",
      "name": "Rainbow Energy",
      "artist": "Takumi Akabane",
      "supertype": "Energy",
      "subtypes": [
        "Special"
      ],
      "rules": [
        "Attach Rainbow Energy to 1 of your Pokémon. While in play, Rainbow Energy counts as every type of basic Energy but only provides 1 Energy at a time. (Doesn't count as a basic Energy card when not in play.) When you attach this card from your hand to 1 of your Pokémon, it does 10 damage to that Pokémon. (Don't apply Weakness and Resistance.)"
      ],
      "rarity": "Rare Holo"
    },
    {
      "set": "base5",
      "cardNum": "16",
      "name": "Rocket's Sneak Attack",
      "artist": "Ken Sugimori",
      "supertype": "Trainer",
      "rules": [
        "Look at your opponent's hand. If he or she has any Trainer cards, choose 1 of them. Your opponent shuffles that card into his or her deck."
      ],
      "rarity": "Rare Holo"
    },
    {
      "set": "base5",
      "cardNum": "18",
      "name": "Dark Alakazam",
      "artist": "Ken Sugimori",
      "supertype": "Pokémon",
      "flavorText": "Almost as if it were being controlled by something else, it never changes expressions, even in the middle of battle.",
      "types": [
        "Psychic"
      ],
      "subtypes": [
        "Stage 2"
      ],
      "hp": "60",
      "level": "30",
      "evolvesFrom": "Dark Kadabra",
      "rarity": "Rare",
      "attacks": [
        {
          "name": "Teleport Blast",
          "cost": [
            "Psychic",
            "Psychic",
            "Colorless"
          ],
          "convertedEnergyCost": 3,
          "damage": "30",
          "text": "You may switch Dark Alakazam with 1 of your Benched Pokémon. (Do the damage before switching the Pokémon.)"
        },
        {
          "name": "Mind Shock",
          "cost": [
            "Psychic",
            "Psychic",
            "Psychic"
          ],
          "convertedEnergyCost": 3,
          "damage": "40",
          "text": "Don't apply Weakness and Resistance for this attack. (Any other effects that would happen after applying Weakness and Resistance still happen.)"
        }
      ],
      "weaknesses": [
        {
          "type": "Psychic",
          "value": "×2"
        }
      ],
      "retreatCost": [
        "Colorless",
        "Colorless",
        "Colorless"
      ],
      "pokedexNumbers": [
        65
      ]
    },
    {
      "set": "base5",
      "cardNum": "19",
      "name": "Dark Arbok",
      "artist": "Mitsuhiro Arita",
      "supertype": "Pokémon",
      "flavorText": "Freezes its prey with its stare. If you should encounter one, remember not to look into its eyes.",
      "types": [
        "Grass"
      ],
      "subtypes": [
        "Stage 1"
      ],
      "hp": "60",
      "level": "25",
      "evolvesFrom": "Ekans",
      "rarity": "Rare",
      "attacks": [
        {
          "name": "Stare",
          "cost": [
            "Grass",
            "Grass"
          ],
          "convertedEnergyCost": 2,
          "damage": "",
          "text": "Choose 1 of your opponent's Pokémon. This attack does 10 damage to that Pokémon. Don't apply Weakness and Resistance for this attack. (Any other effects that would happen after applying Weakness and Resistance still happen.) If that Pokémon has a Pokémon Power, that power stops working until the end of your opponent's next turn."
        },
        {
          "name": "Poison Vapor",
          "cost": [
            "Grass",
            "Grass",
            "Grass"
          ],
          "convertedEnergyCost": 3,
          "damage": "10",
          "text": "The Defending Pokémon is now Poisoned. This attack does 10 damage to each of your opponent's Benched Pokémon. (Don't apply Weakness and Resistance for Benched Pokémon.)"
        }
      ],
      "weaknesses": [
        {
          "type": "Psychic",
          "value": "×2"
        }
      ],
      "retreatCost": [
        "Colorless",
        "Colorless"
      ],
      "pokedexNumbers": [
        24
      ]
    },
    {
      "set": "base5",
      "cardNum": "20",
      "name": "Dark Blastoise",
      "artist": "Mitsuhiro Arita",
      "supertype": "Pokémon",
      "flavorText": "An aggressive Pokémon that tackles anything it sees.",
      "types": [
        "Water"
      ],
      "subtypes": [
        "Stage 2"
      ],
      "hp": "70",
      "level": "28",
      "evolvesFrom": "Dark Wartortle",
      "rarity": "Rare",
      "attacks": [
        {
          "name": "Hydrocannon",
          "cost": [
            "Water",
            "Water"
          ],
          "convertedEnergyCost": 2,
          "damage": "30+",
          "text": "Does 30 damage plus 20 more damage for each Water Energy attached to Dark Blastoise but not used to pay for this attack. You can't add more than 40 damage in this way."
        },
        {
          "name": "Rocket Tackle",
          "cost": [
            "Water",
            "Colorless",
            "Colorless"
          ],
          "convertedEnergyCost": 3,
          "damage": "40",
          "text": "Dark Blastoise does 10 damage to itself. Flip a coin. If heads, prevent all damage done to Dark Blastoise during your opponent's next turn. (Any other effects of attacks still happen.)"
        }
      ],
      "weaknesses": [
        {
          "type": "Lightning",
          "value": "×2"
        }
      ],
      "retreatCost": [
        "Colorless",
        "Colorless"
      ],
      "pokedexNumbers": [
        9
      ]
    },
    {
      "set": "base5",
      "cardNum": "21",
      "name": "Dark Charizard",
      "artist": "Ken Sugimori",
      "supertype": "Pokémon",
      "flavorText": "Seemingly possessed, it spews fire like a volcano, trying to burn all it sees.",
      "types": [
        "Fire"
      ],
      "subtypes": [
        "Stage 2"
      ],
      "hp": "80",
      "level": "38",
      "evolvesFrom": "Dark Charmeleon",
      "rarity": "Rare",
      "attacks": [
        {
          "name": "Nail Flick",
          "cost": [
            "Colorless"
          ],
          "convertedEnergyCost": 1,
          "damage": "10",
          "text": ""
        },
        {
          "name": "Continuous Fireball",
          "cost": [
            "Fire",
            "Fire"
          ],
          "convertedEnergyCost": 2,
          "damage": "50×",
          "text": "Flip a number of coins equal to the number of Fire Energy cards attached to Dark Charizard. This attack does 50 damage times the number of heads. Discard a number of Fire Energy cards attached to Dark Charizard equal to the number of heads."
        }
      ],
      "weaknesses": [
        {
          "type": "Water",
          "value": "×2"
        }
      ],
      "resistances": [
        {
          "type": "Fighting",
          "value": "-30"
        }
      ],
      "retreatCost": [
        "Colorless",
        "Colorless",
        "Colorless"
      ],
      "pokedexNumbers": [
        6
      ]
    },
    {
      "set": "base5",
      "cardNum": "23",
      "name": "Dark Dugtrio",
      "artist": "Kagemaru Himeno",
      "supertype": "Pokémon",
      "flavorText": "Digs large sinkholes in the ground and tries to trap its enemies in them.",
      "types": [
        "Fighting"
      ],
      "subtypes": [
        "Stage 1"
      ],
      "hp": "50",
      "level": "18",
      "evolvesFrom": "Diglett",
      "rarity": "Rare",
      "abilities": [
        {
          "name": "Sinkhole",
          "text": "Whenever your opponent's Active Pokémon retreats, your opponent flips a coin. If tails, this power does 20 damage to that Pokémon. (Don't apply Weakness and Resistance.) This power stops working while Dark Dugtrio is Asleep, Confused, or Paralyzed.",
          "type": "Pokémon Power"
        }
      ],
      "attacks": [
        {
          "name": "Knock Down",
          "cost": [
            "Fighting",
            "Fighting"
          ],
          "convertedEnergyCost": 2,
          "damage": "20+",
          "text": "Your opponent flips a coin. If tails, this attack does 20 damage plus 20 more damage; if heads, this attack does 20 damage."
        }
      ],
      "weaknesses": [
        {
          "type": "Grass",
          "value": "×2"
        }
      ],
      "resistances": [
        {
          "type": "Lightning",
          "value": "-30"
        }
      ],
      "retreatCost": [
        "Colorless",
        "Colorless"
      ],
      "pokedexNumbers": [
        51
      ]
    },
    {
      "set": "base5",
      "cardNum": "22",
      "name": "Dark Dragonite",
      "artist": "Mitsuhiro Arita",
      "supertype": "Pokémon",
      "flavorText": "Sometimes called \"The God of Destruction.\" Its wings are able to support it in spite of its massive weight.",
      "types": [
        "Colorless"
      ],
      "subtypes": [
        "Stage 2"
      ],
      "hp": "70",
      "level": "33",
      "evolvesFrom": "Dark Dragonair",
      "rarity": "Rare",
      "abilities": [
        {
          "name": "Summon Minions",
          "text": "When you play Dark Dragonite from your hand, search your deck for up to 2 Basic Pokémon and put them onto your Bench. Shuffle your deck afterward.",
          "type": "Pokémon Power"
        }
      ],
      "attacks": [
        {
          "name": "Giant Tail",
          "cost": [
            "Colorless",
            "Colorless",
            "Colorless",
            "Colorless"
          ],
          "convertedEnergyCost": 4,
          "damage": "70",
          "text": "Flip a coin. If tails, this attack does nothing."
        }
      ],
      "resistances": [
        {
          "type": "Fighting",
          "value": "-30"
        }
      ],
      "retreatCost": [
        "Colorless",
        "Colorless"
      ],
      "pokedexNumbers": [
        149
      ]
    },
    {
      "set": "base5",
      "cardNum": "24",
      "name": "Dark Golbat",
      "artist": "Mitsuhiro Arita",
      "supertype": "Pokémon",
      "flavorText": "Sneaks up silently on its prey and attacks it from behind, sometimes killing it with one bite.",
      "types": [
        "Grass"
      ],
      "subtypes": [
        "Stage 1"
      ],
      "hp": "50",
      "level": "25",
      "evolvesFrom": "Zubat",
      "evolvesTo": [
        "Crobat"
      ],
      "rarity": "Rare",
      "abilities": [
        {
          "name": "Sneak Attack",
          "text": "When you play Dark Golbat from your hand, you may choose 1 of your opponent's Pokémon. If you do, Dark Golbat does 10 damage to that Pokémon. Apply Weakness and Resistance.",
          "type": "Pokémon Power"
        }
      ],
      "attacks": [
        {
          "name": "Flitter",
          "cost": [
            "Grass",
            "Grass"
          ],
          "convertedEnergyCost": 2,
          "damage": "",
          "text": "Choose 1 of your opponent's Pokémon. This attack does 20 damage to that Pokémon. Don't apply Weakness and Resistance for this attack. (Any other effects that would happen after applying Weakness and Resistance still happen.)"
        }
      ],
      "weaknesses": [
        {
          "type": "Psychic",
          "value": "×2"
        }
      ],
      "resistances": [
        {
          "type": "Fighting",
          "value": "-30"
        }
      ],
      "pokedexNumbers": [
        42
      ]
    },
    {
      "set": "base5",
      "cardNum": "25",
      "name": "Dark Gyarados",
      "artist": "Kagemaru Himeno",
      "supertype": "Pokémon",
      "flavorText": "Normally found only in the deep ocean, it has recently been seen in shallow waters as well.",
      "types": [
        "Water"
      ],
      "subtypes": [
        "Stage 1"
      ],
      "hp": "70",
      "level": "31",
      "evolvesFrom": "Magikarp",
      "rarity": "Rare",
      "abilities": [
        {
          "name": "Final Beam",
          "text": "When Dark Gyarados is Knocked Out by an attack, flip a coin. If heads, this power does 20 damage for each Water Energy attached to Dark Gyarados to the Pokémon that Knocked Out Dark Gyarados. Apply Weakness and Resistance. This power doesn't work if Dark Gyarados is Asleep, Confused, or Paralyzed.",
          "type": "Pokémon Power"
        }
      ],
      "attacks": [
        {
          "name": "Ice Beam",
          "cost": [
            "Water",
            "Water",
            "Water"
          ],
          "convertedEnergyCost": 3,
          "damage": "30",
          "text": "Flip a coin. If heads, the Defending Pokémon is now Paralyzed."
        }
      ],
      "weaknesses": [
        {
          "type": "Grass",
          "value": "×2"
        }
      ],
      "resistances": [
        {
          "type": "Fighting",
          "value": "-30"
        }
      ],
      "retreatCost": [
        "Colorless",
        "Colorless"
      ],
      "pokedexNumbers": [
        130
      ]
    },
    {
      "set": "base5",
      "cardNum": "27",
      "name": "Dark Machamp",
      "artist": "Mitsuhiro Arita",
      "supertype": "Pokémon",
      "flavorText": "It is almost impossible to defend against a Machamp's four powerful arms.",
      "types": [
        "Fighting"
      ],
      "subtypes": [
        "Stage 2"
      ],
      "hp": "70",
      "level": "30",
      "evolvesFrom": "Dark Machoke",
      "rarity": "Rare",
      "attacks": [
        {
          "name": "Mega Punch",
          "cost": [
            "Fighting",
            "Fighting"
          ],
          "convertedEnergyCost": 2,
          "damage": "30",
          "text": ""
        },
        {
          "name": "Fling",
          "cost": [
            "Fighting",
            "Fighting",
            "Fighting",
            "Colorless"
          ],
          "convertedEnergyCost": 4,
          "damage": "",
          "text": "Your opponent shuffles his or her Active Pokémon and all cards attached to it into his or her deck. This attack can't be used if your opponent has no Benched Pokémon."
        }
      ],
      "weaknesses": [
        {
          "type": "Psychic",
          "value": "×2"
        }
      ],
      "retreatCost": [
        "Colorless",
        "Colorless",
        "Colorless"
      ],
      "pokedexNumbers": [
        68
      ]
    },
    {
      "set": "base5",
      "cardNum": "26",
      "name": "Dark Hypno",
      "artist": "Kagemaru Himeno",
      "supertype": "Pokémon",
      "flavorText": "Carries a pendulum with it always. Sometimes appears near less-traveled roads and schools at dusk.",
      "types": [
        "Psychic"
      ],
      "subtypes": [
        "Stage 1"
      ],
      "hp": "60",
      "level": "26",
      "evolvesFrom": "Drowzee",
      "rarity": "Rare",
      "attacks": [
        {
          "name": "Psypunch",
          "cost": [
            "Psychic"
          ],
          "convertedEnergyCost": 1,
          "damage": "20",
          "text": ""
        },
        {
          "name": "Bench Manipulation",
          "cost": [
            "Psychic",
            "Psychic",
            "Colorless"
          ],
          "convertedEnergyCost": 3,
          "damage": "20×",
          "text": "Your opponent flips a number of coins equal to the number of Pokémon on his or her Bench. This attack does 20 damage times the number of tails. Don't apply Weakness and Resistance for this attack. (Any other effects that would happen after applying Weakness and Resistance still happen.)"
        }
      ],
      "weaknesses": [
        {
          "type": "Psychic",
          "value": "×2"
        }
      ],
      "retreatCost": [
        "Colorless",
        "Colorless"
      ],
      "pokedexNumbers": [
        97
      ]
    },
    {
      "set": "base5",
      "cardNum": "28",
      "name": "Dark Magneton",
      "artist": "Miki Tanaka",
      "supertype": "Pokémon",
      "flavorText": "The number of incidents of hackers using Magnetons to damage computer systems is steadily increasing.",
      "types": [
        "Lightning"
      ],
      "subtypes": [
        "Stage 1"
      ],
      "hp": "60",
      "level": "26",
      "evolvesFrom": "Magnemite",
      "evolvesTo": [
        "Magnezone"
      ],
      "rarity": "Rare",
      "attacks": [
        {
          "name": "Sonicboom",
          "cost": [
            "Colorless",
            "Colorless"
          ],
          "convertedEnergyCost": 2,
          "damage": "20",
          "text": "Don't apply Weakness and Resistance for this attack. (Any other effects that would happen after applying Weakness and Resistance still happen.)"
        },
        {
          "name": "Magnetic Lines",
          "cost": [
            "Lightning",
            "Lightning"
          ],
          "convertedEnergyCost": 2,
          "damage": "30",
          "text": "If the Defending Pokémon has any basic Energy cards attached to it, choose 1 of them. If your opponent has any Benched Pokémon, choose 1 of them and attach that Energy card to it."
        }
      ],
      "weaknesses": [
        {
          "type": "Fighting",
          "value": "×2"
        }
      ],
      "retreatCost": [
        "Colorless",
        "Colorless"
      ],
      "pokedexNumbers": [
        82
      ]
    },
    {
      "set": "base5",
      "cardNum": "30",
      "name": "Dark Vileplume",
      "artist": "Kagemaru Himeno",
      "supertype": "Pokémon",
      "flavorText": "Perhaps because of their strong-smelling pollen, other Pokémon do not approach areas where Vileplumes live.",
      "types": [
        "Grass"
      ],
      "subtypes": [
        "Stage 2"
      ],
      "hp": "60",
      "level": "29",
      "evolvesFrom": "Dark Gloom",
      "rarity": "Rare",
      "abilities": [
        {
          "name": "Hay Fever",
          "text": "No Trainer cards can be played. This power stops working while Dark Vileplume is Asleep, Confused, or Paralyzed.",
          "type": "Pokémon Power"
        }
      ],
      "attacks": [
        {
          "name": "Petal Whirlwind",
          "cost": [
            "Grass",
            "Grass",
            "Grass"
          ],
          "convertedEnergyCost": 3,
          "damage": "30×",
          "text": "Flip a coins. This attack does 30 damage times the number of heads. If you get 2 or more heads, Dark Vileplume is now Confused (after doing damage)."
        }
      ],
      "weaknesses": [
        {
          "type": "Fighting",
          "value": "×2"
        }
      ],
      "retreatCost": [
        "Colorless",
        "Colorless"
      ],
      "pokedexNumbers": [
        45
      ]
    },
    {
      "set": "base5",
      "cardNum": "29",
      "name": "Dark Slowbro",
      "artist": "Mitsuhiro Arita",
      "supertype": "Pokémon",
      "flavorText": "It loves nothing better than to be left alone, and so sometimes ends up being manipulated by unscrupulous people.",
      "types": [
        "Psychic"
      ],
      "subtypes": [
        "Stage 1"
      ],
      "hp": "60",
      "level": "27",
      "evolvesFrom": "Slowpoke",
      "rarity": "Rare",
      "abilities": [
        {
          "name": "Reel In",
          "text": "When you play Dark Slowbro from your hand, choose up to 3 Basic Pokémon and/or Evolution cards from your discard pile and put them into your hand.",
          "type": "Pokémon Power"
        }
      ],
      "attacks": [
        {
          "name": "Fickle Attack",
          "cost": [
            "Psychic",
            "Psychic"
          ],
          "convertedEnergyCost": 2,
          "damage": "40",
          "text": "Flip a coin. If tails, this attack does nothing."
        }
      ],
      "weaknesses": [
        {
          "type": "Psychic",
          "value": "×2"
        }
      ],
      "retreatCost": [
        "Colorless",
        "Colorless"
      ],
      "pokedexNumbers": [
        80
      ]
    },
    {
      "set": "base5",
      "cardNum": "31",
      "name": "Dark Weezing",
      "artist": "Shin-ichi Yoshida",
      "supertype": "Pokémon",
      "flavorText": "Researchers have observed these Pokémon reproducing in industrial waste sites.",
      "types": [
        "Grass"
      ],
      "subtypes": [
        "Stage 1"
      ],
      "hp": "60",
      "level": "24",
      "evolvesFrom": "Koffing",
      "rarity": "Rare",
      "attacks": [
        {
          "name": "Mass Explosion",
          "cost": [
            "Grass",
            "Colorless"
          ],
          "convertedEnergyCost": 2,
          "damage": "20×",
          "text": "Does 20 damage times the total number of Koffings, Weezings, and Dark Weezings in play (Apply Weakness and Resistance.). Then, this attack does 20 damage to each Koffing, Weezing, and Dark Weezing (even your own). Don't apply Weakness and Resistance."
        },
        {
          "name": "Stun Gas",
          "cost": [
            "Grass",
            "Grass",
            "Grass"
          ],
          "convertedEnergyCost": 3,
          "damage": "20",
          "text": "Flip a coin. If heads, the Defending Pokémon is now Poisoned; if tails, the Defending Pokémon is now Paralyzed."
        }
      ],
      "weaknesses": [
        {
          "type": "Psychic",
          "value": "×2"
        }
      ],
      "retreatCost": [
        "Colorless"
      ],
      "pokedexNumbers": [
        110
      ]
    },
    {
      "set": "base5",
      "cardNum": "32",
      "name": "Dark Charmeleon",
      "artist": "Kagemaru Himeno",
      "supertype": "Pokémon",
      "flavorText": "Its tail is incredibly strong, able to lift up to 5 adult men.",
      "types": [
        "Fire"
      ],
      "subtypes": [
        "Stage 1"
      ],
      "hp": "50",
      "level": "23",
      "evolvesFrom": "Charmander",
      "evolvesTo": [
        "Charizard"
      ],
      "rarity": "Uncommon",
      "attacks": [
        {
          "name": "Tail Slap",
          "cost": [
            "Colorless",
            "Colorless"
          ],
          "convertedEnergyCost": 2,
          "damage": "20",
          "text": ""
        },
        {
          "name": "Fireball",
          "cost": [
            "Fire",
            "Fire",
            "Fire"
          ],
          "convertedEnergyCost": 3,
          "damage": "70",
          "text": "Use this attack only if there are any Fire Energy cards attached to Dark Charmeleon. Flip a coin. If heads, discard 1 of those Energy cards. If tails, this attack does nothing (not even damage)."
        }
      ],
      "weaknesses": [
        {
          "type": "Water",
          "value": "×2"
        }
      ],
      "retreatCost": [
        "Colorless",
        "Colorless"
      ],
      "pokedexNumbers": [
        5
      ]
    },
    {
      "set": "base5",
      "cardNum": "35",
      "name": "Dark Flareon",
      "artist": "Mitsuhiro Arita",
      "supertype": "Pokémon",
      "flavorText": "A Pokémon with a hot temper that can't be controlled once it's angered. Capable of breathing flames hotter than 3000°.",
      "types": [
        "Fire"
      ],
      "subtypes": [
        "Stage 1"
      ],
      "hp": "50",
      "level": "23",
      "evolvesFrom": "Eevee",
      "rarity": "Uncommon",
      "attacks": [
        {
          "name": "Rage",
          "cost": [
            "Colorless"
          ],
          "convertedEnergyCost": 1,
          "damage": "10+",
          "text": "Does 10 damage plus 10 more damage for each damage counter on Dark Flareon."
        },
        {
          "name": "Playing with Fire",
          "cost": [
            "Fire",
            "Fire"
          ],
          "convertedEnergyCost": 2,
          "damage": "30+",
          "text": "Use this attack only if there are any Fire Energy cards attached to Dark Flareon. Flip a coin. If heads, discard 1 of those Energy cards and this attack does 30 damage plus 20 more damage; if tails, this attack does 30 damage."
        }
      ],
      "weaknesses": [
        {
          "type": "Water",
          "value": "×2"
        }
      ],
      "retreatCost": [
        "Colorless"
      ],
      "pokedexNumbers": [
        136
      ]
    },
    {
      "set": "base5",
      "cardNum": "33",
      "name": "Dark Dragonair",
      "artist": "Kagemaru Himeno",
      "supertype": "Pokémon",
      "flavorText": "As is fitting for a legendary Pokémon, it has many strange powers, including the ability to make rain or snow fall.",
      "types": [
        "Colorless"
      ],
      "subtypes": [
        "Stage 1"
      ],
      "hp": "60",
      "level": "28",
      "evolvesFrom": "Dratini",
      "evolvesTo": [
        "Dragonite"
      ],
      "rarity": "Uncommon",
      "abilities": [
        {
          "name": "Evolutionary Light",
          "text": "Once during your turn (before your attack), you may search your deck for an Evolution card. Show it to your opponent and put it into your hand. Shuffle your deck afterward. This power can't be used if Dark Dragonair is Asleep, Confused, or Paralyzed.",
          "type": "Pokémon Power"
        }
      ],
      "attacks": [
        {
          "name": "Tail Strike",
          "cost": [
            "Colorless",
            "Colorless",
            "Colorless"
          ],
          "convertedEnergyCost": 3,
          "damage": "20+",
          "text": "Flip a coin. If heads, this attack does 20 damage plus 20 more damage; if tails, this attack does 20 damage."
        }
      ],
      "resistances": [
        {
          "type": "Psychic",
          "value": "-30"
        }
      ],
      "retreatCost": [
        "Colorless",
        "Colorless"
      ],
      "pokedexNumbers": [
        148
      ]
    },
    {
      "set": "base5",
      "cardNum": "34",
      "name": "Dark Electrode",
      "artist": "Ken Sugimori",
      "supertype": "Pokémon",
      "flavorText": "Some researchers hypothesize that Electrode may actually be a form of energy instead of having an actual body.",
      "types": [
        "Lightning"
      ],
      "subtypes": [
        "Stage 1"
      ],
      "hp": "60",
      "level": "24",
      "evolvesFrom": "Voltorb",
      "rarity": "Uncommon",
      "attacks": [
        {
          "name": "Rolling Tackle",
          "cost": [
            "Colorless"
          ],
          "convertedEnergyCost": 1,
          "damage": "10",
          "text": ""
        },
        {
          "name": "Energy Bomb",
          "cost": [
            "Lightning",
            "Lightning"
          ],
          "convertedEnergyCost": 2,
          "damage": "30",
          "text": "Take all Energy cards attached to Dark Electrode and attach them to your Benched Pokémon (in any way you choose). If you have no Benched Pokémon, discard all Energy cards attached to Dark Electrode."
        }
      ],
      "weaknesses": [
        {
          "type": "Fighting",
          "value": "×2"
        }
      ],
      "retreatCost": [
        "Colorless"
      ],
      "pokedexNumbers": [
        101
      ]
    },
    {
      "set": "base5",
      "cardNum": "36",
      "name": "Dark Gloom",
      "artist": "Kagemaru Himeno",
      "supertype": "Pokémon",
      "flavorText": "Its pollen has such a strong smell that it even confuses itself at times.",
      "types": [
        "Grass"
      ],
      "subtypes": [
        "Stage 1"
      ],
      "hp": "50",
      "level": "21",
      "evolvesFrom": "Oddish",
      "evolvesTo": [
        "Vileplume",
        "Bellossom"
      ],
      "rarity": "Uncommon",
      "abilities": [
        {
          "name": "Pollen Stench",
          "text": "Once during your turn (before your attack), you may flip a coin. If heads, the Defending Pokémon is now Confused; if tails, your Active Pokémon is now Confused. This power can't be used if Dark Gloom is Asleep, Confused, or Paralyzed.",
          "type": "Pokémon Power"
        }
      ],
      "attacks": [
        {
          "name": "Poisonpowder",
          "cost": [
            "Grass",
            "Grass"
          ],
          "convertedEnergyCost": 2,
          "damage": "10",
          "text": "The Defending Pokémon is now Poisoned."
        }
      ],
      "weaknesses": [
        {
          "type": "Fire",
          "value": "×2"
        }
      ],
      "retreatCost": [
        "Colorless",
        "Colorless"
      ],
      "pokedexNumbers": [
        44
      ]
    },
    {
      "set": "base5",
      "cardNum": "37",
      "name": "Dark Golduck",
      "artist": "Mitsuhiro Arita",
      "supertype": "Pokémon",
      "flavorText": "When Psyducks evolve, their headaches disappear and they find themselves in possession of formidable mental powers.",
      "types": [
        "Water"
      ],
      "subtypes": [
        "Stage 1"
      ],
      "hp": "60",
      "level": "23",
      "evolvesFrom": "Psyduck",
      "rarity": "Uncommon",
      "attacks": [
        {
          "name": "Third Eye",
          "cost": [
            "Psychic"
          ],
          "convertedEnergyCost": 1,
          "damage": "",
          "text": "Discard 1 Energy card attached to Dark Golduck in order to draw up to 3 cards."
        },
        {
          "name": "Super Psy",
          "cost": [
            "Psychic",
            "Psychic",
            "Colorless"
          ],
          "convertedEnergyCost": 3,
          "damage": "50",
          "text": ""
        }
      ],
      "weaknesses": [
        {
          "type": "Lightning",
          "value": "×2"
        }
      ],
      "retreatCost": [
        "Colorless",
        "Colorless"
      ],
      "pokedexNumbers": [
        55
      ]
    },
    {
      "set": "base5",
      "cardNum": "38",
      "name": "Dark Jolteon",
      "artist": "Mitsuhiro Arita",
      "supertype": "Pokémon",
      "flavorText": "A dangerous Pokémon when angered. It likes to playfully shock people with the electricity it stores within its body.",
      "types": [
        "Lightning"
      ],
      "subtypes": [
        "Stage 1"
      ],
      "hp": "50",
      "level": "23",
      "evolvesFrom": "Eevee",
      "rarity": "Uncommon",
      "attacks": [
        {
          "name": "Lightning Flash",
          "cost": [
            "Lightning"
          ],
          "convertedEnergyCost": 1,
          "damage": "20",
          "text": "If the Defending Pokémon tries to attack during your opponent's next turn, your opponent flips a coin. If tails, that attack does nothing."
        },
        {
          "name": "Thunder Attack",
          "cost": [
            "Lightning",
            "Lightning",
            "Colorless"
          ],
          "convertedEnergyCost": 3,
          "damage": "30",
          "text": "Flip a coin. If heads, the Defending Pokémon is now Paralyzed. If tails, Dark Jolteon does 10 damage to itself."
        }
      ],
      "weaknesses": [
        {
          "type": "Fighting",
          "value": "×2"
        }
      ],
      "retreatCost": [
        "Colorless"
      ],
      "pokedexNumbers": [
        135
      ]
    },
    {
      "set": "base5",
      "cardNum": "39",
      "name": "Dark Kadabra",
      "artist": "Kagemaru Himeno",
      "supertype": "Pokémon",
      "flavorText": "Some people say that Kadabras are responsible for many of the mysterious events reported in the news.",
      "types": [
        "Psychic"
      ],
      "subtypes": [
        "Stage 1"
      ],
      "hp": "50",
      "level": "24",
      "evolvesFrom": "Abra",
      "evolvesTo": [
        "Alakazam"
      ],
      "rarity": "Uncommon",
      "abilities": [
        {
          "name": "Matter Exchange",
          "text": "Once during your turn (before your attack), you may discard a card from your hand in order to draw a card. This power can't be used if Dark Kadabra is Asleep, Confused, or Paralyzed.",
          "type": "Pokémon Power"
        }
      ],
      "attacks": [
        {
          "name": "Mind Shock",
          "cost": [
            "Psychic",
            "Psychic"
          ],
          "convertedEnergyCost": 2,
          "damage": "30",
          "text": "Don't apply Weakness and Resistance for this attack. (Any other effects that would happen after applying Weakness and Resistance still happen.)"
        }
      ],
      "weaknesses": [
        {
          "type": "Psychic",
          "value": "×2"
        }
      ],
      "retreatCost": [
        "Colorless",
        "Colorless"
      ],
      "pokedexNumbers": [
        64
      ]
    },
    {
      "set": "base5",
      "cardNum": "40",
      "name": "Dark Machoke",
      "artist": "Mitsuhiro Arita",
      "supertype": "Pokémon",
      "flavorText": "While normally peaceful and friendly, the number of incidents involving cruel Machokes is rising.",
      "types": [
        "Fighting"
      ],
      "subtypes": [
        "Stage 1"
      ],
      "hp": "60",
      "level": "28",
      "evolvesFrom": "Machop",
      "evolvesTo": [
        "Machamp"
      ],
      "rarity": "Uncommon",
      "attacks": [
        {
          "name": "Drag Off",
          "cost": [
            "Fighting",
            "Fighting",
            "Colorless"
          ],
          "convertedEnergyCost": 3,
          "damage": "20",
          "text": "Before doing damage, choose 1 of your opponent's Benched Pokémon and switch it with the Defending Pokémon. Do the damage to the new Defending Pokémon. This attack can't be used if your opponent has no Benched Pokémon."
        },
        {
          "name": "Knock Back",
          "cost": [
            "Fighting",
            "Fighting",
            "Colorless"
          ],
          "convertedEnergyCost": 3,
          "damage": "30",
          "text": "If your opponent has any Benched Pokémon, he or she chooses 1 of them and switches it with the Defending Pokémon. (Do the damage before switching the Pokémon.)"
        }
      ],
      "weaknesses": [
        {
          "type": "Psychic",
          "value": "×2"
        }
      ],
      "retreatCost": [
        "Colorless",
        "Colorless"
      ],
      "pokedexNumbers": [
        67
      ]
    },
    {
      "set": "base5",
      "cardNum": "41",
      "name": "Dark Muk",
      "artist": "Kagemaru Himeno",
      "supertype": "Pokémon",
      "flavorText": "Muks appear suddenly, spreading sludge everywhere. Whenever one appears in a city, panic ensues.",
      "types": [
        "Grass"
      ],
      "subtypes": [
        "Stage 1"
      ],
      "hp": "60",
      "level": "25",
      "evolvesFrom": "Grimer",
      "rarity": "Uncommon",
      "abilities": [
        {
          "name": "Sticky Goo",
          "text": "As long as Dark Muk is your Active Pokémon, your opponent pays ColorlessColorless more to retreat his or her Active Pokémon. This power stops working while Dark Muk is Asleep, Confused, or Paralyzed.",
          "type": "Pokémon Power"
        }
      ],
      "attacks": [
        {
          "name": "Sludge Punch",
          "cost": [
            "Grass",
            "Grass"
          ],
          "convertedEnergyCost": 2,
          "damage": "20",
          "text": "The Defending Pokémon is now Poisoned."
        }
      ],
      "weaknesses": [
        {
          "type": "Psychic",
          "value": "×2"
        }
      ],
      "retreatCost": [
        "Colorless",
        "Colorless"
      ],
      "pokedexNumbers": [
        89
      ]
    },
    {
      "set": "base5",
      "cardNum": "42",
      "name": "Dark Persian",
      "artist": "Shin-ichi Yoshida",
      "supertype": "Pokémon",
      "flavorText": "Popular with women because of its beautiful fur. The leader of the Rockets keeps one as a pet.",
      "types": [
        "Colorless"
      ],
      "subtypes": [
        "Stage 1"
      ],
      "hp": "60",
      "level": "28",
      "evolvesFrom": "Meowth",
      "rarity": "Uncommon",
      "attacks": [
        {
          "name": "Fascinate",
          "cost": [
            "Colorless"
          ],
          "convertedEnergyCost": 1,
          "damage": "",
          "text": "Flip a coin. If heads, choose 1 of your opponent's Benched Pokémon and switch it with the Defending Pokémon. This attack can't be used if your opponent has no Benched Pokémon."
        },
        {
          "name": "Poison Claws",
          "cost": [
            "Colorless",
            "Colorless"
          ],
          "convertedEnergyCost": 2,
          "damage": "10",
          "text": "Flip a coin. If heads, the Defending Pokémon is now Poisoned."
        }
      ],
      "weaknesses": [
        {
          "type": "Fighting",
          "value": "×2"
        }
      ],
      "resistances": [
        {
          "type": "Psychic",
          "value": "-30"
        }
      ],
      "pokedexNumbers": [
        53
      ]
    },
    {
      "set": "base5",
      "cardNum": "43",
      "name": "Dark Primeape",
      "artist": "Mitsuhiro Arita",
      "supertype": "Pokémon",
      "flavorText": "Although Primeapes have always been mean, lately they seem to be becoming even more vicious and frenzied.",
      "types": [
        "Fighting"
      ],
      "subtypes": [
        "Stage 1"
      ],
      "hp": "60",
      "level": "23",
      "evolvesFrom": "Mankey",
      "rarity": "Uncommon",
      "abilities": [
        {
          "name": "Frenzy",
          "text": "If Dark Primeape does any damage while it's Confused (even to itself), it does 30 more damage.",
          "type": "Pokémon Power"
        }
      ],
      "attacks": [
        {
          "name": "Frenzied Attack",
          "cost": [
            "Fighting",
            "Fighting"
          ],
          "convertedEnergyCost": 2,
          "damage": "40",
          "text": "Dark Primeape is now Confused (after doing damage)."
        }
      ],
      "weaknesses": [
        {
          "type": "Psychic",
          "value": "×2"
        }
      ],
      "retreatCost": [
        "Colorless"
      ],
      "pokedexNumbers": [
        57
      ]
    },
    {
      "set": "base5",
      "cardNum": "45",
      "name": "Dark Vaporeon",
      "artist": "Mitsuhiro Arita",
      "supertype": "Pokémon",
      "flavorText": "A Pokémon capable of controlling water, so it is capable of creating giant whirlpools.",
      "types": [
        "Water"
      ],
      "subtypes": [
        "Stage 1"
      ],
      "hp": "60",
      "level": "28",
      "evolvesFrom": "Eevee",
      "rarity": "Uncommon",
      "attacks": [
        {
          "name": "Bite",
          "cost": [
            "Colorless",
            "Colorless",
            "Colorless"
          ],
          "convertedEnergyCost": 3,
          "damage": "30",
          "text": ""
        },
        {
          "name": "Whirlpool",
          "cost": [
            "Water",
            "Water",
            "Colorless"
          ],
          "convertedEnergyCost": 3,
          "damage": "20",
          "text": "If the Defending Pokémon has any Energy cards attached to it, choose 1 of them and discard it."
        }
      ],
      "weaknesses": [
        {
          "type": "Lightning",
          "value": "×2"
        }
      ],
      "retreatCost": [
        "Colorless"
      ],
      "pokedexNumbers": [
        134
      ]
    },
    {
      "set": "base5",
      "cardNum": "44",
      "name": "Dark Rapidash",
      "artist": "Kagemaru Himeno",
      "supertype": "Pokémon",
      "flavorText": "A wild, uncontrollable Pokémon. When running, it looks like a comet streaking through the sky.",
      "types": [
        "Fire"
      ],
      "subtypes": [
        "Stage 1"
      ],
      "hp": "60",
      "level": "24",
      "evolvesFrom": "Ponyta",
      "rarity": "Uncommon",
      "attacks": [
        {
          "name": "Rear Kick",
          "cost": [
            "Colorless",
            "Colorless"
          ],
          "convertedEnergyCost": 2,
          "damage": "20",
          "text": ""
        },
        {
          "name": "Flame Pillar",
          "cost": [
            "Fire",
            "Fire"
          ],
          "convertedEnergyCost": 2,
          "damage": "30",
          "text": "You may discard 1 Fire Energy card attached to Dark Rapidash when you use this attack. If you do and if your opponent has any Benched Pokémon, choose 1 of them and this attack does 10 damage to it. (Don't apply Weakness and Resistance for Benched Pokémon.)"
        }
      ],
      "weaknesses": [
        {
          "type": "Water",
          "value": "×2"
        }
      ],
      "pokedexNumbers": [
        78
      ]
    },
    {
      "set": "base5",
      "cardNum": "46",
      "name": "Dark Wartortle",
      "artist": "Kagemaru Himeno",
      "supertype": "Pokémon",
      "flavorText": "A Pokémon with a negative attitude, it hides in its shell whenever it's in a bad mood—which is often.",
      "types": [
        "Water"
      ],
      "subtypes": [
        "Stage 1"
      ],
      "hp": "60",
      "level": "21",
      "evolvesFrom": "Squirtle",
      "evolvesTo": [
        "Blastoise"
      ],
      "rarity": "Uncommon",
      "attacks": [
        {
          "name": "Doubleslap",
          "cost": [
            "Water"
          ],
          "convertedEnergyCost": 1,
          "damage": "10×",
          "text": "Flip 2 coins. This attack does 10 damage times the number of heads."
        },
        {
          "name": "Mirror Shell",
          "cost": [
            "Water",
            "Colorless"
          ],
          "convertedEnergyCost": 2,
          "damage": "",
          "text": "If an attack does damage to Dark Wartortle during your opponent's next turn (even if Dark Wartortle is Knocked Out), Dark Wartortle attacks the Defending Pokémon for an equal amount of damage."
        }
      ],
      "weaknesses": [
        {
          "type": "Lightning",
          "value": "×2"
        }
      ],
      "retreatCost": [
        "Colorless"
      ],
      "pokedexNumbers": [
        8
      ]
    },
    {
      "set": "base5",
      "cardNum": "47",
      "name": "Magikarp",
      "artist": "Kagemaru Himeno",
      "supertype": "Pokémon",
      "flavorText": "Recent research has revealed the presence of dragon DNA in this species of Pokémon.",
      "types": [
        "Water"
      ],
      "subtypes": [
        "Basic"
      ],
      "hp": "30",
      "level": "6",
      "evolvesTo": [
        "Gyarados"
      ],
      "rarity": "Uncommon",
      "attacks": [
        {
          "name": "Flop",
          "cost": [
            "Colorless"
          ],
          "convertedEnergyCost": 1,
          "damage": "10",
          "text": ""
        },
        {
          "name": "Rapid Evolution",
          "cost": [
            "Water",
            "Water",
            "Water"
          ],
          "convertedEnergyCost": 3,
          "damage": "",
          "text": "Search your deck for an Evolution card named Gyarados or Dark Gyarados and put it on Magikarp. (This counts as evolving Magikarp.) Shuffle your deck afterward."
        }
      ],
      "weaknesses": [
        {
          "type": "Lightning",
          "value": "×2"
        }
      ],
      "retreatCost": [
        "Colorless"
      ],
      "pokedexNumbers": [
        129
      ]
    },
    {
      "set": "base5",
      "cardNum": "48",
      "name": "Porygon",
      "artist": "Keiji Kinebuchi",
      "supertype": "Pokémon",
      "flavorText": "More and more people play the slots every day, trying to win a Porygon.",
      "types": [
        "Colorless"
      ],
      "subtypes": [
        "Basic"
      ],
      "hp": "40",
      "level": "26",
      "evolvesTo": [
        "Porygon2"
      ],
      "rarity": "Uncommon",
      "attacks": [
        {
          "name": "Conversion 1",
          "cost": [
            "Colorless"
          ],
          "convertedEnergyCost": 1,
          "damage": "",
          "text": "If the Defending Pokémon has a Weakness, you may change it to a type of your choice other than Colorless."
        },
        {
          "name": "Psybeam",
          "cost": [
            "Colorless",
            "Colorless",
            "Colorless"
          ],
          "convertedEnergyCost": 3,
          "damage": "20",
          "text": "Flip a coin. If heads, the Defending Pokémon is now Confused."
        }
      ],
      "weaknesses": [
        {
          "type": "Fighting",
          "value": "×2"
        }
      ],
      "resistances": [
        {
          "type": "Psychic",
          "value": "-30"
        }
      ],
      "pokedexNumbers": [
        137
      ]
    },
    {
      "set": "base5",
      "cardNum": "50",
      "name": "Charmander",
      "artist": "Kagemaru Himeno",
      "supertype": "Pokémon",
      "flavorText": "Many people find it cute and try to hold it, only to be burned by its tail.",
      "types": [
        "Fire"
      ],
      "subtypes": [
        "Basic"
      ],
      "hp": "40",
      "level": "9",
      "evolvesTo": [
        "Charmeleon"
      ],
      "rarity": "Common",
      "abilities": [
        {
          "name": "Gather Fire",
          "text": "Once during your turn (before your attack), you may take 1 Fire Energy card attached to 1 of your other Pokémon and attach it to Charmander. This power can't be used if Charmander is Asleep, Confused, or Paralyzed.",
          "type": "Pokémon Power"
        }
      ],
      "attacks": [
        {
          "name": "Fire Tail",
          "cost": [
            "Fire"
          ],
          "convertedEnergyCost": 1,
          "damage": "20",
          "text": ""
        }
      ],
      "weaknesses": [
        {
          "type": "Water",
          "value": "×2"
        }
      ],
      "retreatCost": [
        "Colorless"
      ],
      "pokedexNumbers": [
        4
      ]
    },
    {
      "set": "base5",
      "cardNum": "51",
      "name": "Dark Raticate",
      "artist": "Shin-ichi Yoshida",
      "supertype": "Pokémon",
      "flavorText": "A Raticate's front teeth are incredibly powerful; it can destroy a two-story house with them in 5 minutes.",
      "types": [
        "Colorless"
      ],
      "subtypes": [
        "Stage 1"
      ],
      "hp": "50",
      "level": "25",
      "evolvesFrom": "Rattata",
      "rarity": "Common",
      "attacks": [
        {
          "name": "Gnaw",
          "cost": [
            "Colorless",
            "Colorless"
          ],
          "convertedEnergyCost": 2,
          "damage": "20",
          "text": ""
        },
        {
          "name": "Hyper Fang",
          "cost": [
            "Colorless",
            "Colorless",
            "Colorless"
          ],
          "convertedEnergyCost": 3,
          "damage": "50",
          "text": "Flip a coin. If tails, this attack does nothing."
        }
      ],
      "weaknesses": [
        {
          "type": "Fighting",
          "value": "×2"
        }
      ],
      "resistances": [
        {
          "type": "Psychic",
          "value": "-30"
        }
      ],
      "retreatCost": [
        "Colorless"
      ],
      "pokedexNumbers": [
        20
      ]
    },
    {
      "set": "base5",
      "cardNum": "52",
      "name": "Diglett",
      "artist": "Sumiyoshi Kizuki",
      "supertype": "Pokémon",
      "flavorText": "It follows Onixes in their tunnels, looking for scraps of food they have left behind.",
      "types": [
        "Fighting"
      ],
      "subtypes": [
        "Basic"
      ],
      "hp": "40",
      "level": "15",
      "evolvesTo": [
        "Dugtrio"
      ],
      "rarity": "Common",
      "attacks": [
        {
          "name": "Dig Under",
          "cost": [
            "Fighting"
          ],
          "convertedEnergyCost": 1,
          "damage": "",
          "text": "Choose 1 of your opponent's Pokémon. This attack does 10 damage to that Pokémon. Don't apply Weakness and Resistance for this attack. (Any other effects that would happen after applying Weakness and Resistance still happen.)"
        },
        {
          "name": "Scratch",
          "cost": [
            "Fighting",
            "Colorless"
          ],
          "convertedEnergyCost": 2,
          "damage": "20",
          "text": ""
        }
      ],
      "weaknesses": [
        {
          "type": "Grass",
          "value": "×2"
        }
      ],
      "resistances": [
        {
          "type": "Lightning",
          "value": "-30"
        }
      ],
      "pokedexNumbers": [
        50
      ]
    },
    {
      "set": "base5",
      "cardNum": "49",
      "name": "Abra",
      "artist": "Sumiyoshi Kizuki",
      "supertype": "Pokémon",
      "flavorText": "It teleports itself away from danger, making it difficult to capture.",
      "types": [
        "Psychic"
      ],
      "subtypes": [
        "Basic"
      ],
      "hp": "40",
      "level": "14",
      "evolvesTo": [
        "Kadabra"
      ],
      "rarity": "Common",
      "attacks": [
        {
          "name": "Vanish",
          "cost": [
            "Psychic"
          ],
          "convertedEnergyCost": 1,
          "damage": "",
          "text": "Shuffle Abra into your deck. (Discard all cards attached to Abra.)"
        },
        {
          "name": "Psyshock",
          "cost": [
            "Psychic"
          ],
          "convertedEnergyCost": 1,
          "damage": "10",
          "text": "Flip a coin. If heads, the Defending Pokémon is now Paralyzed."
        }
      ],
      "weaknesses": [
        {
          "type": "Psychic",
          "value": "×2"
        }
      ],
      "retreatCost": [
        "Colorless"
      ],
      "pokedexNumbers": [
        63
      ]
    },
    {
      "set": "base5",
      "cardNum": "53",
      "name": "Dratini",
      "artist": "Kagemaru Himeno",
      "supertype": "Pokémon",
      "flavorText": "The capture of the first Dratini inspired the search for other legendary Pokémon.",
      "types": [
        "Colorless"
      ],
      "subtypes": [
        "Basic"
      ],
      "hp": "40",
      "level": "12",
      "evolvesTo": [
        "Dragonair"
      ],
      "rarity": "Common",
      "attacks": [
        {
          "name": "Wrap",
          "cost": [
            "Colorless",
            "Colorless"
          ],
          "convertedEnergyCost": 2,
          "damage": "10",
          "text": "Flip a coin. If heads, the Defending Pokémon is now Paralyzed."
        }
      ],
      "resistances": [
        {
          "type": "Psychic",
          "value": "-30"
        }
      ],
      "retreatCost": [
        "Colorless"
      ],
      "pokedexNumbers": [
        147
      ]
    },
    {
      "set": "base5",
      "cardNum": "54",
      "name": "Drowzee",
      "artist": "Kagemaru Himeno",
      "supertype": "Pokémon",
      "flavorText": "Not popular with girls because of its attitude. Can often be heard muttering to itself in a low voice.",
      "types": [
        "Psychic"
      ],
      "subtypes": [
        "Basic"
      ],
      "hp": "50",
      "level": "10",
      "evolvesTo": [
        "Hypno"
      ],
      "rarity": "Common",
      "abilities": [
        {
          "name": "Long-Distance Hypnosis",
          "text": "Once during your turn (before your attack), you may flip a coin. If heads, the Defending Pokémon is now Asleep; if tails, your Active Pokémon is now Asleep. This power can't be used if Drowzee is Asleep, Confused, or Paralyzed.",
          "type": "Pokémon Power"
        }
      ],
      "attacks": [
        {
          "name": "Nightmare",
          "cost": [
            "Psychic",
            "Colorless"
          ],
          "convertedEnergyCost": 2,
          "damage": "10",
          "text": "The Defending Pokémon is now Asleep."
        }
      ],
      "weaknesses": [
        {
          "type": "Psychic",
          "value": "×2"
        }
      ],
      "retreatCost": [
        "Colorless"
      ],
      "pokedexNumbers": [
        96
      ]
    },
    {
      "set": "base5",
      "cardNum": "55",
      "name": "Eevee",
      "artist": "Atsuko Nishida",
      "supertype": "Pokémon",
      "flavorText": "A rare and unique Pokémon about which little is known, as few have been captured.",
      "types": [
        "Colorless"
      ],
      "subtypes": [
        "Basic"
      ],
      "hp": "40",
      "level": "9",
      "evolvesTo": [
        "Vaporeon",
        "Jolteon",
        "Flareon",
        "Sylveon",
        "Espeon",
        "Umbreon",
        "Leafeon",
        "Glaceon"
      ],
      "rarity": "Common",
      "attacks": [
        {
          "name": "Tackle",
          "cost": [
            "Colorless"
          ],
          "convertedEnergyCost": 1,
          "damage": "10",
          "text": ""
        },
        {
          "name": "Sand-attack",
          "cost": [
            "Colorless",
            "Colorless"
          ],
          "convertedEnergyCost": 2,
          "damage": "10",
          "text": "If the Defending Pokémon tries to attack during your opponent's next turn, your opponent flips a coin. If tails, that attack does nothing."
        }
      ],
      "weaknesses": [
        {
          "type": "Fighting",
          "value": "×2"
        }
      ],
      "resistances": [
        {
          "type": "Psychic",
          "value": "-30"
        }
      ],
      "retreatCost": [
        "Colorless"
      ],
      "pokedexNumbers": [
        133
      ]
    },
    {
      "set": "base5",
      "cardNum": "56",
      "name": "Ekans",
      "artist": "Ken Sugimori",
      "supertype": "Pokémon",
      "flavorText": "A carnivore that swallows its prey whole. Pidgeys and Spearows are its favorite food.",
      "types": [
        "Grass"
      ],
      "subtypes": [
        "Basic"
      ],
      "hp": "50",
      "level": "15",
      "evolvesTo": [
        "Arbok"
      ],
      "rarity": "Common",
      "attacks": [
        {
          "name": "Bite",
          "cost": [
            "Colorless"
          ],
          "convertedEnergyCost": 1,
          "damage": "10",
          "text": ""
        },
        {
          "name": "Poison Sting",
          "cost": [
            "Grass",
            "Grass"
          ],
          "convertedEnergyCost": 2,
          "damage": "20",
          "text": "Flip a coin. If heads, the Defending Pokémon is now Poisoned."
        }
      ],
      "weaknesses": [
        {
          "type": "Psychic",
          "value": "×2"
        }
      ],
      "retreatCost": [
        "Colorless"
      ],
      "pokedexNumbers": [
        23
      ]
    },
    {
      "set": "base5",
      "cardNum": "57",
      "name": "Grimer",
      "artist": "Kagemaru Himeno",
      "supertype": "Pokémon",
      "flavorText": "It has recently been found that Grimers are formed in waste-processing plants, and can move into towns via sewers.",
      "types": [
        "Grass"
      ],
      "subtypes": [
        "Basic"
      ],
      "hp": "40",
      "level": "10",
      "evolvesTo": [
        "Muk"
      ],
      "rarity": "Common",
      "attacks": [
        {
          "name": "Poison Gas",
          "cost": [
            "Grass"
          ],
          "convertedEnergyCost": 1,
          "damage": "",
          "text": "The Defending Pokémon is now Asleep."
        },
        {
          "name": "Sticky Hands",
          "cost": [
            "Grass",
            "Grass"
          ],
          "convertedEnergyCost": 2,
          "damage": "10+",
          "text": "Flip a coin. If heads, this attack does 10 damage plus 20 more damage and the Defending Pokémon is now Paralyzed; if tails, this attack does 10 damage."
        }
      ],
      "weaknesses": [
        {
          "type": "Psychic",
          "value": "×2"
        }
      ],
      "retreatCost": [
        "Colorless"
      ],
      "pokedexNumbers": [
        88
      ]
    },
    {
      "set": "base5",
      "cardNum": "58",
      "name": "Koffing",
      "artist": "Sumiyoshi Kizuki",
      "supertype": "Pokémon",
      "flavorText": "First discovered in a weapons factory, this Pokémon can now be found almost anywhere.",
      "types": [
        "Grass"
      ],
      "subtypes": [
        "Basic"
      ],
      "hp": "40",
      "level": "12",
      "evolvesTo": [
        "Weezing"
      ],
      "rarity": "Common",
      "attacks": [
        {
          "name": "Tackle",
          "cost": [
            "Colorless"
          ],
          "convertedEnergyCost": 1,
          "damage": "10",
          "text": ""
        },
        {
          "name": "Poison Gas",
          "cost": [
            "Grass",
            "Colorless"
          ],
          "convertedEnergyCost": 2,
          "damage": "20",
          "text": "Flip a coin. If heads, the Defending Pokémon is now Poisoned."
        }
      ],
      "weaknesses": [
        {
          "type": "Psychic",
          "value": "×2"
        }
      ],
      "retreatCost": [
        "Colorless"
      ],
      "pokedexNumbers": [
        109
      ]
    },
    {
      "set": "base5",
      "cardNum": "62",
      "name": "Meowth",
      "artist": "Atsuko Nishida",
      "supertype": "Pokémon",
      "flavorText": "A popular Pokémon that earns money for its owner with its \"Pay Day\" ability.",
      "types": [
        "Colorless"
      ],
      "subtypes": [
        "Basic"
      ],
      "hp": "40",
      "level": "10",
      "evolvesTo": [
        "Persian"
      ],
      "rarity": "Common",
      "attacks": [
        {
          "name": "Coin Hurl",
          "cost": [
            "Colorless",
            "Colorless"
          ],
          "convertedEnergyCost": 2,
          "damage": "",
          "text": "Choose 1 of your opponent's Pokémon and flip a coin. If heads, this attack does 20 damage to that Pokémon. Don't apply Weakness and Resistance for this attack. (Any other effects that would happen after applying Weakness and Resistance still happen.)"
        }
      ],
      "weaknesses": [
        {
          "type": "Fighting",
          "value": "×2"
        }
      ],
      "resistances": [
        {
          "type": "Psychic",
          "value": "-30"
        }
      ],
      "retreatCost": [
        "Colorless"
      ],
      "pokedexNumbers": [
        52
      ]
    },
    {
      "set": "base5",
      "cardNum": "59",
      "name": "Machop",
      "artist": "Ken Sugimori",
      "supertype": "Pokémon",
      "flavorText": "It's said that not even pro wrestlers can take down a Machop.",
      "types": [
        "Fighting"
      ],
      "subtypes": [
        "Basic"
      ],
      "hp": "50",
      "level": "24",
      "evolvesTo": [
        "Machoke"
      ],
      "rarity": "Common",
      "attacks": [
        {
          "name": "Punch",
          "cost": [
            "Colorless",
            "Colorless"
          ],
          "convertedEnergyCost": 2,
          "damage": "20",
          "text": ""
        },
        {
          "name": "Kick",
          "cost": [
            "Fighting",
            "Colorless",
            "Colorless"
          ],
          "convertedEnergyCost": 3,
          "damage": "30",
          "text": ""
        }
      ],
      "weaknesses": [
        {
          "type": "Psychic",
          "value": "×2"
        }
      ],
      "retreatCost": [
        "Colorless"
      ],
      "pokedexNumbers": [
        66
      ]
    },
    {
      "set": "base5",
      "cardNum": "60",
      "name": "Magnemite",
      "artist": "Miki Tanaka",
      "supertype": "Pokémon",
      "flavorText": "It is said that enough Magnemites and Magnetons gather in one place, they can create a powerful magnetic barrier.",
      "types": [
        "Lightning"
      ],
      "subtypes": [
        "Basic"
      ],
      "hp": "40",
      "level": "12",
      "evolvesTo": [
        "Magneton"
      ],
      "rarity": "Common",
      "attacks": [
        {
          "name": "Tackle",
          "cost": [
            "Colorless",
            "Colorless"
          ],
          "convertedEnergyCost": 2,
          "damage": "20",
          "text": ""
        },
        {
          "name": "Magnetism",
          "cost": [
            "Lightning",
            "Colorless"
          ],
          "convertedEnergyCost": 2,
          "damage": "10+",
          "text": "Does 10 damage plus 10 more damage for each Magnemite, Magneton, and Dark Magneton on your Bench."
        }
      ],
      "weaknesses": [
        {
          "type": "Fighting",
          "value": "×2"
        }
      ],
      "retreatCost": [
        "Colorless"
      ],
      "pokedexNumbers": [
        81
      ]
    },
    {
      "set": "base5",
      "cardNum": "61",
      "name": "Mankey",
      "artist": "Sumiyoshi Kizuki",
      "supertype": "Pokémon",
      "flavorText": "Normally friendly, it quickly becomes angry if it doesn't get what it wants.",
      "types": [
        "Fighting"
      ],
      "subtypes": [
        "Basic"
      ],
      "hp": "40",
      "level": "14",
      "evolvesTo": [
        "Primeape"
      ],
      "rarity": "Common",
      "attacks": [
        {
          "name": "Mischief",
          "cost": [
            "Colorless"
          ],
          "convertedEnergyCost": 1,
          "damage": "",
          "text": "Shuffle your opponent's deck."
        },
        {
          "name": "Anger",
          "cost": [
            "Fighting",
            "Colorless"
          ],
          "convertedEnergyCost": 2,
          "damage": "20+",
          "text": "Flip a coin. If heads, this attack does 20 damage plus 20 more damage; if tails, this attack does 20 damage."
        }
      ],
      "weaknesses": [
        {
          "type": "Psychic",
          "value": "×2"
        }
      ],
      "pokedexNumbers": [
        56
      ]
    },
    {
      "set": "base5",
      "cardNum": "65",
      "name": "Psyduck",
      "artist": "Mitsuhiro Arita",
      "supertype": "Pokémon",
      "flavorText": "It is often seen holding its head in its paws, as if it were suffering from a headache.",
      "types": [
        "Water"
      ],
      "subtypes": [
        "Basic"
      ],
      "hp": "50",
      "level": "16",
      "evolvesTo": [
        "Golduck"
      ],
      "rarity": "Common",
      "attacks": [
        {
          "name": "Dizziness",
          "cost": [
            "Psychic"
          ],
          "convertedEnergyCost": 1,
          "damage": "",
          "text": "Draw a card."
        },
        {
          "name": "Water Gun",
          "cost": [
            "Water",
            "Colorless"
          ],
          "convertedEnergyCost": 2,
          "damage": "20+",
          "text": "Does 20 damage plus 10 more damage for each Water Energy attached to Psyduck but not used to pay for this attack. You can't add more than 20 damage in this way."
        }
      ],
      "weaknesses": [
        {
          "type": "Lightning",
          "value": "×2"
        }
      ],
      "retreatCost": [
        "Colorless"
      ],
      "pokedexNumbers": [
        54
      ]
    },
    {
      "set": "base5",
      "cardNum": "63",
      "name": "Oddish",
      "artist": "Kagemaru Himeno",
      "supertype": "Pokémon",
      "flavorText": "It wanders around at night sowing its seeds to create more Oddishes.",
      "types": [
        "Grass"
      ],
      "subtypes": [
        "Basic"
      ],
      "hp": "50",
      "level": "21",
      "evolvesTo": [
        "Gloom"
      ],
      "rarity": "Common",
      "attacks": [
        {
          "name": "Sleep Powder",
          "cost": [
            "Grass"
          ],
          "convertedEnergyCost": 1,
          "damage": "",
          "text": "The Defending Pokémon is now Asleep."
        },
        {
          "name": "Poisonpowder",
          "cost": [
            "Grass"
          ],
          "convertedEnergyCost": 1,
          "damage": "",
          "text": "The Defending Pokémon is now Poisoned."
        }
      ],
      "weaknesses": [
        {
          "type": "Fire",
          "value": "×2"
        }
      ],
      "retreatCost": [
        "Colorless"
      ],
      "pokedexNumbers": [
        43
      ]
    },
    {
      "set": "base5",
      "cardNum": "64",
      "name": "Ponyta",
      "artist": "Atsuko Nishida",
      "supertype": "Pokémon",
      "flavorText": "A gentle grass-eater, it will allow riders on its back. However, anyone attempting to do so must be careful not to get burned.",
      "types": [
        "Fire"
      ],
      "subtypes": [
        "Basic"
      ],
      "hp": "50",
      "level": "15",
      "evolvesTo": [
        "Rapidash"
      ],
      "rarity": "Common",
      "attacks": [
        {
          "name": "Ember",
          "cost": [
            "Fire",
            "Colorless"
          ],
          "convertedEnergyCost": 2,
          "damage": "30",
          "text": "Discard 1 Fire Energy card attached to Ponyta in order to use this attack."
        }
      ],
      "weaknesses": [
        {
          "type": "Water",
          "value": "×2"
        }
      ],
      "retreatCost": [
        "Colorless"
      ],
      "pokedexNumbers": [
        77
      ]
    },
    {
      "set": "base5",
      "cardNum": "68",
      "name": "Squirtle",
      "artist": "Atsuko Nishida",
      "supertype": "Pokémon",
      "flavorText": "Cute Pokémon that charms people with its innocent eyes. Loves swimming all day long.",
      "types": [
        "Water"
      ],
      "subtypes": [
        "Basic"
      ],
      "hp": "50",
      "level": "16",
      "evolvesTo": [
        "Wartortle"
      ],
      "rarity": "Common",
      "attacks": [
        {
          "name": "Shell Attack",
          "cost": [
            "Colorless",
            "Colorless"
          ],
          "convertedEnergyCost": 2,
          "damage": "20",
          "text": ""
        }
      ],
      "weaknesses": [
        {
          "type": "Lightning",
          "value": "×2"
        }
      ],
      "retreatCost": [
        "Colorless"
      ],
      "pokedexNumbers": [
        7
      ]
    },
    {
      "set": "base5",
      "cardNum": "69",
      "name": "Voltorb",
      "artist": "Ken Sugimori",
      "supertype": "Pokémon",
      "flavorText": "Usually seen only in power plants, it is sometimes seen in towns, apparently using the power lines to travel.",
      "types": [
        "Lightning"
      ],
      "subtypes": [
        "Basic"
      ],
      "hp": "40",
      "level": "13",
      "evolvesTo": [
        "Electrode"
      ],
      "rarity": "Common",
      "attacks": [
        {
          "name": "Speed Ball",
          "cost": [
            "Lightning"
          ],
          "convertedEnergyCost": 1,
          "damage": "20",
          "text": ""
        }
      ],
      "weaknesses": [
        {
          "type": "Fighting",
          "value": "×2"
        }
      ],
      "retreatCost": [
        "Colorless"
      ],
      "pokedexNumbers": [
        100
      ]
    },
    {
      "set": "base5",
      "cardNum": "66",
      "name": "Rattata",
      "artist": "Atsuko Nishida",
      "supertype": "Pokémon",
      "flavorText": "Loves to eat walnuts, chestnuts, cheese, and milk.",
      "types": [
        "Colorless"
      ],
      "subtypes": [
        "Basic"
      ],
      "hp": "40",
      "level": "12",
      "evolvesTo": [
        "Raticate"
      ],
      "rarity": "Common",
      "abilities": [
        {
          "name": "Trickery",
          "text": "Once during your turn (before your attack), you may switch 1 of your Prizes with the top card of your deck. This power can't be used if Rattata is Asleep, Confused, or Paralyzed.",
          "type": "Pokémon Power"
        }
      ],
      "attacks": [
        {
          "name": "Quick Attack",
          "cost": [
            "Colorless"
          ],
          "convertedEnergyCost": 1,
          "damage": "10+",
          "text": "Flip a coin. If heads, this attack does 10 damage plus 10 more damage; if tails, this attack does 10 damage."
        }
      ],
      "weaknesses": [
        {
          "type": "Fighting",
          "value": "×2"
        }
      ],
      "resistances": [
        {
          "type": "Psychic",
          "value": "-30"
        }
      ],
      "pokedexNumbers": [
        19
      ]
    },
    {
      "set": "base5",
      "cardNum": "67",
      "name": "Slowpoke",
      "artist": "Sumiyoshi Kizuki",
      "supertype": "Pokémon",
      "flavorText": "Although it knows how to fish, no other intelligent behavior has been detected in it.",
      "types": [
        "Psychic"
      ],
      "subtypes": [
        "Basic"
      ],
      "hp": "50",
      "level": "16",
      "evolvesTo": [
        "Slowbro",
        "Slowking"
      ],
      "rarity": "Common",
      "attacks": [
        {
          "name": "Afternoon Nap",
          "cost": [
            "Colorless"
          ],
          "convertedEnergyCost": 1,
          "damage": "",
          "text": "Search your deck for a Psychic Energy card and attach it to Slowpoke. Shuffle your deck afterward."
        },
        {
          "name": "Headbutt",
          "cost": [
            "Psychic"
          ],
          "convertedEnergyCost": 1,
          "damage": "10",
          "text": ""
        }
      ],
      "weaknesses": [
        {
          "type": "Psychic",
          "value": "×2"
        }
      ],
      "retreatCost": [
        "Colorless"
      ],
      "pokedexNumbers": [
        79
      ]
    },
    {
      "set": "base5",
      "cardNum": "71",
      "name": "Here Comes Team Rocket!",
      "artist": "Ken Sugimori",
      "supertype": "Trainer",
      "rules": [
        "Each player plays with his or her Prize cards face up for the rest of the game."
      ],
      "rarity": "Rare"
    },
    {
      "set": "base5",
      "cardNum": "70",
      "name": "Zubat",
      "artist": "Mitsuhiro Arita",
      "supertype": "Pokémon",
      "flavorText": "Lives in dark caves. Can occasionally be seen at night, when it flies in search of food.",
      "types": [
        "Grass"
      ],
      "subtypes": [
        "Basic"
      ],
      "hp": "40",
      "level": "9",
      "evolvesTo": [
        "Golbat"
      ],
      "rarity": "Common",
      "attacks": [
        {
          "name": "Ram",
          "cost": [
            "Colorless"
          ],
          "convertedEnergyCost": 1,
          "damage": "10",
          "text": ""
        },
        {
          "name": "Bite",
          "cost": [
            "Grass",
            "Colorless"
          ],
          "convertedEnergyCost": 2,
          "damage": "20",
          "text": ""
        }
      ],
      "weaknesses": [
        {
          "type": "Psychic",
          "value": "×2"
        }
      ],
      "resistances": [
        {
          "type": "Fighting",
          "value": "-30"
        }
      ],
      "pokedexNumbers": [
        41
      ]
    },
    {
      "set": "base5",
      "cardNum": "72",
      "name": "Rocket's Sneak Attack",
      "artist": "Ken Sugimori",
      "supertype": "Trainer",
      "rules": [
        "Look at your opponent's hand. If he or she has any Trainer cards, choose 1 of them. Your opponent shuffles that card into his or her deck."
      ],
      "rarity": "Rare"
    },
    {
      "set": "base5",
      "cardNum": "73",
      "name": "The Boss's Way",
      "artist": "Ken Sugimori",
      "supertype": "Trainer",
      "rules": [
        "Search your deck for an Evolution card with Dark in its name. Show it to your opponent and put it into your hand. Shuffle your deck afterward."
      ],
      "rarity": "Uncommon"
    },
    {
      "set": "base5",
      "cardNum": "74",
      "name": "Challenge!",
      "artist": "Kagemaru Himeno",
      "supertype": "Trainer",
      "rules": [
        "Ask your opponent if he or she accepts your challenge. If your opponent declines (or if both Benches are full), draw 2 cards. If your opponent accepts, each of you searches your decks for any number of Basic Pokémon cards and puts them face down onto your Benches. (A player can't do this if his or her Bench is full.) When you both have finished, shuffle your decks and turn those cards face up."
      ],
      "rarity": "Uncommon"
    },
    {
      "set": "base5",
      "cardNum": "77",
      "name": "Nightly Garbage Run",
      "artist": "Sumiyoshi Kizuki",
      "supertype": "Trainer",
      "subtypes": [
        "Rocket's Secret Machine"
      ],
      "rules": [
        "Choose up to 3 Basic Pokémon cards, Evolution cards, and/or basic Energy cards from your discard pile. Show them to your opponent and shuffle them into your deck."
      ],
      "rarity": "Uncommon"
    },
    {
      "set": "base5",
      "cardNum": "75",
      "name": "Digger",
      "artist": "Sumiyoshi Kizuki",
      "supertype": "Trainer",
      "subtypes": [
        "Rocket's Secret Machine"
      ],
      "rules": [
        "Flip a coin. If tails, do 10 damage to your Active Pokémon. If heads, your opponent flips a coin. If tails, your opponent does 10 damage to his or her Active Pokémon. If heads, you flip a coin. Keep doing this until a player gets tails."
      ],
      "rarity": "Uncommon"
    },
    {
      "set": "base5",
      "cardNum": "78",
      "name": "Goop Gas Attack",
      "artist": "Sumiyoshi Kizuki",
      "supertype": "Trainer",
      "rules": [
        "All Pokémon Powers stop working until the end of your opponent's next turn."
      ],
      "rarity": "Common"
    },
    {
      "set": "base5",
      "cardNum": "76",
      "name": "Imposter Oak's Revenge",
      "artist": "Ken Sugimori",
      "supertype": "Trainer",
      "rules": [
        "Discard a card from your hand in order to play this card. Your opponent shuffles his or her hand into his or her deck, then draws 4 cards."
      ],
      "rarity": "Uncommon"
    },
    {
      "set": "base5",
      "cardNum": "79",
      "name": "Sleep!",
      "artist": "Sumiyoshi Kizuki",
      "supertype": "Trainer",
      "subtypes": [
        "Rocket's Secret Machine"
      ],
      "rules": [
        "Flip a coin. If heads, the Defending Pokémon is now Asleep."
      ],
      "rarity": "Common"
    },
    {
      "set": "base5",
      "cardNum": "80",
      "name": "Rainbow Energy",
      "artist": "Takumi Akabane",
      "supertype": "Energy",
      "subtypes": [
        "Special"
      ],
      "rules": [
        "Attach Rainbow Energy to 1 of your Pokémon. While in play, Rainbow Energy counts as every type of basic Energy but only provides 1 Energy at a time. (Doesn't count as a basic Energy card when not in play.) When you attach this card from your hand to 1 of your Pokémon, it does 10 damage to that Pokémon. (Don't apply Weakness and Resistance.)"
      ],
      "rarity": "Rare"
    },
    {
      "set": "base5",
      "cardNum": "81",
      "name": "Full Heal Energy",
      "artist": "Keiji Kinebuchi",
      "supertype": "Energy",
      "subtypes": [
        "Special"
      ],
      "rules": [
        "If you play this card from your hand, the Pokémon you attach it to is no longer Asleep, Confused, Paralyzed, or Poisoned.",
        "Full Heal Energy provides Colorless energy. (Doesn't count as a basic Energy card.)"
      ],
      "rarity": "Uncommon"
    },
    {
      "set": "base5",
      "cardNum": "82",
      "name": "Potion Energy",
      "artist": "Keiji Kinebuchi",
      "supertype": "Energy",
      "subtypes": [
        "Special"
      ],
      "rules": [
        "If you play this card from your hand, remove 1 damage counter from the Pokémon you attach it to, if it has any.",
        "Potion Energy provides Colorless energy. (Doesn't count as a basic Energy card.)"
      ],
      "rarity": "Uncommon"
    },
    {
      "set": "base5",
      "cardNum": "83",
      "name": "Dark Raichu",
      "artist": "Mitsuhiro Arita",
      "supertype": "Pokémon",
      "flavorText": "Stores up electricity in its body, then suddenly releases it to surprise and shock everyone.",
      "types": [
        "Lightning"
      ],
      "subtypes": [
        "Stage 1"
      ],
      "hp": "70",
      "level": "31",
      "evolvesFrom": "Pikachu",
      "rarity": "Rare Secret",
      "attacks": [
        {
          "name": "Surprise Thunder",
          "cost": [
            "Lightning",
            "Lightning",
            "Lightning"
          ],
          "convertedEnergyCost": 3,
          "damage": "30",
          "text": "Flip a coin. If heads, flip another coin. If the second coin is heads, this attack does 20 damage to each of your opponent's Benched Pokémon. If the second coin is tails, this attack does 10 damage to each of your opponent's Benched Pokémon. (Don't apply Weakness and Resistance for Benched Pokémon.)"
        }
      ],
      "weaknesses": [
        {
          "type": "Fighting",
          "value": "×2"
        }
      ],
      "retreatCost": [
        "Colorless"
      ],
      "pokedexNumbers": [
        26
      ]
    }
  ],
  "datatype": "cards"
}